azure/mgmt/largeinstance/__init__.py
azure/mgmt/largeinstance/_configuration.py
azure/mgmt/largeinstance/_large_instance_mgmt_client.py
azure/mgmt/largeinstance/_patch.py
azure/mgmt/largeinstance/_serialization.py
azure/mgmt/largeinstance/_vendor.py
azure/mgmt/largeinstance/_version.py
azure/mgmt/largeinstance/py.typed
azure/mgmt/largeinstance/aio/__init__.py
azure/mgmt/largeinstance/aio/_configuration.py
azure/mgmt/largeinstance/aio/_large_instance_mgmt_client.py
azure/mgmt/largeinstance/aio/_patch.py
azure/mgmt/largeinstance/aio/operations/__init__.py
azure/mgmt/largeinstance/aio/operations/_azure_large_instance_operations.py
azure/mgmt/largeinstance/aio/operations/_azure_large_storage_instance_operations.py
azure/mgmt/largeinstance/aio/operations/_operations.py
azure/mgmt/largeinstance/aio/operations/_patch.py
azure/mgmt/largeinstance/models/__init__.py
azure/mgmt/largeinstance/models/_large_instance_mgmt_client_enums.py
azure/mgmt/largeinstance/models/_models_py3.py
azure/mgmt/largeinstance/models/_patch.py
azure/mgmt/largeinstance/operations/__init__.py
azure/mgmt/largeinstance/operations/_azure_large_instance_operations.py
azure/mgmt/largeinstance/operations/_azure_large_storage_instance_operations.py
azure/mgmt/largeinstance/operations/_operations.py
azure/mgmt/largeinstance/operations/_patch.py
azure_mgmt_largeinstance-1.0.0b1.dist-info/LICENSE
azure_mgmt_largeinstance-1.0.0b1.dist-info/METADATA
azure_mgmt_largeinstance-1.0.0b1.dist-info/WHEEL
azure_mgmt_largeinstance-1.0.0b1.dist-info/top_level.txt
azure_mgmt_largeinstance-1.0.0b1.dist-info/RECORD
